gnatwriter/__init__.py
gnatwriter/application.py
gnatwriter/controllers/ActivityController.py
gnatwriter/controllers/AssistantController.py
gnatwriter/controllers/AuthorController.py
gnatwriter/controllers/BaseController.py
gnatwriter/controllers/BibliographyController.py
gnatwriter/controllers/ChapterController.py
gnatwriter/controllers/CharacterController.py
gnatwriter/controllers/EventController.py
gnatwriter/controllers/ExportController.py
gnatwriter/controllers/ImageController.py
gnatwriter/controllers/LinkController.py
gnatwriter/controllers/LocationController.py
gnatwriter/controllers/NoteController.py
gnatwriter/controllers/OllamaModelController.py
gnatwriter/controllers/SceneController.py
gnatwriter/controllers/StoryController.py
gnatwriter/controllers/SubmissionController.py
gnatwriter/controllers/UserController.py
gnatwriter/controllers/__init__.py
gnatwriter/models/Activity.py
gnatwriter/models/Assistance.py
gnatwriter/models/Author.py
gnatwriter/models/AuthorStory.py
gnatwriter/models/Base.py
gnatwriter/models/Bibliography.py
gnatwriter/models/BibliographyAuthor.py
gnatwriter/models/Chapter.py
gnatwriter/models/ChapterLink.py
gnatwriter/models/ChapterNote.py
gnatwriter/models/Character.py
gnatwriter/models/CharacterEvent.py
gnatwriter/models/CharacterImage.py
gnatwriter/models/CharacterLink.py
gnatwriter/models/CharacterNote.py
gnatwriter/models/CharacterRelationship.py
gnatwriter/models/CharacterRelationshipTypes.py
gnatwriter/models/CharacterStory.py
gnatwriter/models/CharacterTrait.py
gnatwriter/models/Event.py
gnatwriter/models/EventLink.py
gnatwriter/models/EventNote.py
gnatwriter/models/Image.py
gnatwriter/models/ImageLocation.py
gnatwriter/models/ImageMimeTypes.py
gnatwriter/models/Link.py
gnatwriter/models/LinkLocation.py
gnatwriter/models/LinkScene.py
gnatwriter/models/LinkStory.py
gnatwriter/models/Location.py
gnatwriter/models/LocationNote.py
gnatwriter/models/Note.py
gnatwriter/models/NoteScene.py
gnatwriter/models/NoteStory.py
gnatwriter-0.1.32.dist-info/LICENSE
gnatwriter-0.1.32.dist-info/METADATA
gnatwriter-0.1.32.dist-info/WHEEL
gnatwriter-0.1.32.dist-info/RECORD
