Metadata-Version: 2.1
Name: gnatwriter
Version: 0.1.32
Summary: 
Author: Richard Lucas
Author-email: webmaster@applebiter.com
Requires-Python: >=3.10,<4.0
Classifier: Programming Language :: Python :: 3
Classifier: Programming Language :: Python :: 3.10
Classifier: Programming Language :: Python :: 3.11
Classifier: Programming Language :: Python :: 3.12
